<!DOCTYPE ui:UiBinder SYSTEM "http://dl.google.com/gwt/DTD/xhtml.ent">
<ui:UiBinder xmlns:ui="urn:ui:com.google.gwt.uibinder" xmlns:g="urn:import:com.google.gwt.user.client.ui"
	xmlns:w="urn:import:havis.custom.harting.iso159612.ui.client.widgets">

	<ui:with type="havis.custom.harting.iso159612.utils.Translation" field="i18n" />
	<ui:style>
	.property {
		margin-top:0.5em;
	}
	
	.property tr td:first-child {
		width: 4em;
	}
	</ui:style>
	<g:HTMLPanel>
		<g:HorizontalPanel addStyleNames="{style.property}" verticalAlignment="ALIGN_MIDDLE">
			<g:Label text="{i18n.remotePropertyUrl}" />
			<w:PlaceholderTextBox ui:field="url" placeholder="ws://localhost:80"
				addStyleNames="havis-textBox" />
		</g:HorizontalPanel>		
		<g:HorizontalPanel ui:field="toolbar" addStyleNames="toolbar">
			<g:Button ui:field="apply" text="{i18n.remoteButtonApply}" addStyleNames="toolbar-button" />
		</g:HorizontalPanel>		
	</g:HTMLPanel>
</ui:UiBinder>